mcp_server_dlis/__init__.py
mcp_server_dlis/__main__.py
mcp_server_dlis/dlis_server.py
mcp_server_dlis/tests/__init__.py
mcp_server_dlis/tests/test.py
mcp_server_dlis-0.1.1.dist-info/licenses/LICENSE
mcp_server_dlis-0.1.1.dist-info/METADATA
mcp_server_dlis-0.1.1.dist-info/WHEEL
mcp_server_dlis-0.1.1.dist-info/entry_points.txt
mcp_server_dlis-0.1.1.dist-info/top_level.txt
mcp_server_dlis-0.1.1.dist-info/RECORD
