Metadata-Version: 2.4
Name: mcp_server_dlis
Version: 0.1.1
Summary: A DLIS server implementation for MCP
Home-page: https://github.com/houtj/mcp_server_dlis
Author: Houtj
Classifier: Development Status :: 3 - Alpha
Classifier: Intended Audience :: Developers
Classifier: Programming Language :: Python :: 3
Classifier: Programming Language :: Python :: 3.8
Classifier: Programming Language :: Python :: 3.9
Classifier: Programming Language :: Python :: 3.10
Classifier: Programming Language :: Python :: 3.11
Classifier: License :: OSI Approved :: MIT License
Classifier: Operating System :: OS Independent
Classifier: Topic :: Software Development :: Libraries :: Python Modules
Requires-Python: >=3.8
License-File: LICENSE
Requires-Dist: annotated-types==0.7.0
Requires-Dist: anyio==4.9.0
Requires-Dist: certifi==2025.1.31
Requires-Dist: click==8.1.8
Requires-Dist: dlisio==1.0.3
Requires-Dist: exceptiongroup==1.2.2
Requires-Dist: h11==0.14.0
Requires-Dist: httpcore==1.0.7
Requires-Dist: httpx==0.28.1
Requires-Dist: httpx-sse==0.4.0
Requires-Dist: idna==3.10
Requires-Dist: mcp==1.5.0
Requires-Dist: numpy==2.2.4
Requires-Dist: pydantic==2.10.6
Requires-Dist: pydantic-settings==2.8.1
Requires-Dist: pydantic_core==2.27.2
Requires-Dist: python-dotenv==1.1.0
Requires-Dist: sniffio==1.3.1
Requires-Dist: sse-starlette==2.2.1
Requires-Dist: starlette==0.46.1
Requires-Dist: typing_extensions==4.13.0
Requires-Dist: uvicorn==0.34.0
Dynamic: author
Dynamic: classifier
Dynamic: description
Dynamic: description-content-type
Dynamic: home-page
Dynamic: license-file
Dynamic: requires-dist
Dynamic: requires-python
Dynamic: summary
